Metadata-Version: 2.1
Name: Wicky
Version: 0.1.1
Summary: A libre tool for Wicked Engine development
Home-page: https://github.com/MolassesLover/Wicky
Author: Maeve Garside
Author-email: 60114762+MolassesLover@users.noreply.github.com
License: MIT
Platform: UNKNOWN
License-File: LICENSE.md
